Metadata-Version: 2.1
Name: firefly-api
Version: 0.0.3
Summary: The python API for Firefly, a browser-based particle viewer.
Home-page: https://github.com/agurvich/firefly_api
Author: Alex Gurvich
Author-email: agurvich@u.northwestern.edu
License: UNKNOWN
Platform: UNKNOWN
Classifier: Programming Language :: Python :: 3
Classifier: License :: OSI Approved :: BSD License
Classifier: Operating System :: OS Independent
